swg_python/__init__.py
swg_python/parser.py
swg_python/views.py
swg_python/static/swg_python/specification.js
swg_python/static/swg_python/swagger-editor-bundle.js
swg_python/static/swg_python/swagger-editor-bundle.js.map
swg_python/static/swg_python/swagger-editor.css
swg_python/static/swg_python/swagger-editor.css.map
swg_python/static/swg_python/swagger-editor.js
swg_python/static/swg_python/swagger-editor.js.map
swg_python/static/swg_python/validation.worker.js
swg_python/static/swg_python/validation.worker.js.map
swg_python/templates/.DS_Store
swg_python/templates/swg_python/base.html
swg_python/templates/swg_python/index.html
swg_python/templates/swg_python/redoc.html
swg_python-1.1.7.dist-info/LICENSE
swg_python-1.1.7.dist-info/METADATA
swg_python-1.1.7.dist-info/WHEEL
swg_python-1.1.7.dist-info/entry_points.txt
swg_python-1.1.7.dist-info/top_level.txt
swg_python-1.1.7.dist-info/RECORD
