Metadata-Version: 2.1
Name: swg-python
Version: 1.1.7
Summary: Framework agnostic Swagger parsing library in Python
Home-page: https://github.com/Furkanzmc/swg-python
Author: Furkan Uzumcu
Author-email: furkanuzumcu@gmail.com
License: Public Domain
Keywords: python swagger python-library python-script
Platform: UNKNOWN
Classifier: Development Status :: 4 - Beta
Classifier: Intended Audience :: Developers
Classifier: Topic :: Software Development :: Build Tools
Classifier: License :: Public Domain
Classifier: Programming Language :: Python :: 2.7
Classifier: Programming Language :: Python :: 3
Classifier: Programming Language :: Python :: 3.3
Classifier: Programming Language :: Python :: 3.4
Classifier: Programming Language :: Python :: 3.5
Requires-Dist: pyyaml (==5.1.2)
